alertpy/__init__.py
alertpy-0.0.1.dist-info/METADATA
alertpy-0.0.1.dist-info/WHEEL
alertpy-0.0.1.dist-info/top_level.txt
alertpy-0.0.1.dist-info/RECORD
