Metadata-Version: 2.1
Name: alertpy
Version: 0.0.1
Summary: Python library to support to send various alerts/notifications
Home-page: https://github.com/changukshin/alertpy
Author: Chang-Uk Shin
Author-email: changuk.shin.1991@gmail.com
License: MIT
Keywords: notification,alert
Classifier: License :: OSI Approved :: MIT License
Classifier: Programming Language :: Python
Classifier: Programming Language :: Python :: 3
Classifier: Programming Language :: Python :: 3.6
Classifier: Programming Language :: Python :: 3.7
Classifier: Programming Language :: Python :: 3.8
Classifier: Programming Language :: Python :: 3.9
Classifier: Programming Language :: Python :: 3.10
Classifier: Operating System :: Microsoft :: Windows
Classifier: Operating System :: POSIX :: Linux
Classifier: Operating System :: MacOS
Requires-Python: >=3.6
Provides-Extra: dev
